{
    "_user_information": {
        "_FIRST_NAME": "Tolga",
        "_LAST_NAME": "Karaca",
        "_encoded_password": "1234",
        "_UNIVERSITY_EMAIL": "tolgakaraca@marun.edu.tr",
        "_email": "tolgakaraca90@gmail.com",
        "_address": "Kocaeli",
        "_phone_number": "+90 537 930 79 29"
    },
    "_student_id": {
        "_department_id": {
            "_departmentID": 154,
            "_departmentName": "Chemistry"
        },
        "_entrance_date": 2024,
        "_entrance_rank": 25,
        "_faculty_id": {
            "_FacultyID": 2,
            "_FacultyName": "Science"
        },
        "_id": "154024025"
    },
    "_transcript": {
        "_student_id": {
            "_department_id": {
                "_departmentID": 154,
                "_departmentName": "Chemistry"
            },
            "_entrance_date": 2024,
            "_entrance_rank": 25,
            "_faculty_id": {
                "_FacultyID": 2,
                "_FacultyName": "Science"
            },
            "_id": "154024025"
        },
        "_taken_courses": [],
        "_gpa": 0.0
    },
    "_advisor_id": {
        "_staffId": 25
    },
    "_current_class": 1,
    "_current_courses": []
}